{"file:///Users/wilhelm/Documents/GitHub/archive/willi_uk/1-29Mar":{"assets/images/hashes.json":"Gsx0uKWcu+QETibWicXBvw==","assets/images/whtffffff-172x129.png":"XgbLU/DaxYquko35r7GmYA==","assets/images/greycccccc-172x129.png":"8cLVEz2KPlZsObeFG3zBpQ==","assets/images/orange-172x129.png":"EKo2dZWz70V3Zv54ctRFqQ==","assets/images/0000ffblue-172x129.png":"jfgBfglxw2KIkX91XW6Now==","assets/images/green00ff00-172x129.png":"znj0Z8DRFpv3XIMaY0mHIg==","assets/images/yellow-172x129.png":"7brTIF2lRptklnu26BlgZw==","assets/images/li-128x128-3-128x128.png":"6DfVOezfZFomzaCEtYFtuw==","assets/images/aa-1014x1014.png":"Q6fN9N1xTFKTTcp3rPepgA==","assets/images/mbr-3-361x361.png":"KDqURiB5Exklo9oIf9ZUhw==","assets/images/mbr-4-361x361.png":"Q4TqVSNI8pNtLT7WYgK34A==","assets/images/blogcover-educhallenges-04-2020-696x392.png":"lylkT0TTAokPzwe/xJmMMw==","assets/images/img-2059.jpg":"hmTtRiOra05JKuXD/sPU9Q==","assets/images/07789253-267d-412f-a9f5-a446bf10e768.jpg":"WIdv6gzNrBBLURZgkTrUkw==","assets/images/img-5506-750x1333.jpg":"AjPmha66HYps+pSsAo50TQ==","assets/images/img-4761-750x937.jpg":"bzx2L8Pe4ul7WEMXOt/2dQ==","assets/images/img-4280-750x938.jpg":"skxwafOmVGv0j9z2IDRG5g==","assets/images/img-2960-750x500.jpg":"QFAHuMBTHcXL4qoNg6li8A==","assets/images/calcu-366x458.jpg":"7l7jAqAXih2BHuItZ+oswQ==","assets/images/halt18-20-366x459.jpg":"Zq+fEO5sBcykDDGHImOqYg==","assets/images/chessbd-366x458.jpg":"lSIkaLxm0Sfyg5hh3WTBUw==","assets/images/bauhaus-painting-366x458.jpg":"oiuQ6zAincbtRxff0ZGs9Q==","assets/images/three-tones-blkwht-366x474.jpg":"rEimpVv7PsQc6ORvLjTDnA==","assets/images/pencil-366x459.jpg":"idlgXQPw0mBza9EVkqNTVw==","assets/images/asset-9-366x457.jpg":"hMODedyBxFOsjsBgTokXNQ==","assets/images/img-9751-366x457.jpg":"3l3wuTVqMNpxTQEKqoVeUg==","assets/images/ffwht-time-2-492x377.png":"wnniaeLVECsUbbkhjOSAtw==","assets/images/owlrg-1-492x492.png":"RstS86VePUJ9zusFEOJGuQ==","assets/images/pencil-2-492x492.png":"xuKx+vC5O/gbuGGnBKZn9A==","assets/images/img-9751-366x457.jpeg":"XbS0L8tFZzOsm/ZsiByDnQ==","assets/images/owlrg-492x492.png":"AeVQuxYm0a+PAYvZSEM4lA==","assets/images/ffwht-time-492x377.png":"DgYkZjbi10yfbnyHuE4WsA==","assets/images/halt-creation-01-08-2020-page-1-890x688.png":"vLh0nUgDOX8PcWmoARomUw==","assets/images/halt-creation-01-08-2020-page-8-1488x1150.png":"zefSjdNhj51Mp1m58quZSQ==","assets/images/sculpturewil.jpg":"ATq/Ok2ArxI6QOGbGZxIug==","assets/images/asset-78.png":"NVXIprJnKLk9aD7cryWLjQ==","assets/images/img-2059.jpeg":"KD6M39sDwymZzIz+1dEVcA==","assets/images/asset-32.png":"NMvCo6HHfw1OsJmti/UX2w==","assets/images/fdc4cbed-9cf4-4568-8014-bf41fb1694c0.jpg":"ZtFnw0Dv0Uy/lW5BwW9R1A==","assets/images/img-2353.jpeg":"WiEVNuUouKcJHQZUV5pvaw==","assets/images/img-9652.jpg":"7rvwboIZeMyoLbCPoIxvHg==","assets/images/img-2383.jpeg":"7KuFkps7oy2vKf/GMV4ydA==","assets/images/img-2421.png":"k/myhI1wn4Sh6/BJGuIBEQ==","assets/images/img-2420.png":"VI95DyMA4rrR0y6PTHOhRw==","assets/images/about-meta.jpg":"zkosLjXuTNuqsPAJNdN0cA==","assets/images/img-8271-1076x1346.jpg":"IBypIMtv3O3Pjv8LKXooAQ==","assets/images/sum-calculator-1076x1345.jpeg":"y8sM2yvEvXCefSkPRVMKOw==","assets/images/orange-cirle-1-357x358.png":"2v4JUBQJRH9XTVtQBJUBZA==","assets/images/img-779-3072x4608.png":"OLRXmrHrFOf6R6OfLHYhaQ==","assets/images/img-1467.jpeg":"lqx4v8LtVJMAR4NobHGl3g==","assets/images/halt-creation-01-08-2020-page-3-1240x958.png":"wDXzZErY7FYdZjpx9A3Vfg==","assets/images/halt-creation-01-08-2020-page-3-918x709.png":"gMFKN4Fs+728WKs6Wfs1Ww==","assets/images/halt-creation-01-08-2020-page-4-1078x833.png":"FCoyEmqNtPBxKm3ohofuOQ==","assets/images/24-game-theory-halt-creation-2018.jpg":"+lDXt6VByNTf7+Wn/VfPwA==","assets/images/halt-creation-01-08-2020-page-5-1078x838.png":"Ykd4EhBt4pLXFDl0s0ZFmg==","assets/images/3-ffcc66-halt-creation-2021.png":"gZHmQPXGsECbf2GEPp+MbA==","assets/images/halt-creation-01-08-2020-page-6-1078x827.png":"zqLCFo81iXrqCdMVRz7jxA==","assets/images/img-1128-1078x1617.jpg":"jKKtBjdJx0SPP5PhnnYTaA==","assets/images/halt-creation-01-08-2020-page-7-1078x833.png":"hGcRvjnLZvQRPP4FunW41Q==","assets/images/portfolio-2020-page-17.png":"PJlieQQrIMyHzW3dgHZkfw==","assets/images/halt-creation-01-08-2020-page-9-896x692.png":"H+Hol2OQdo87lSRw8FrCcg==","assets/images/img-5734-900x1125.jpg":"1GbNGMxUPqF5lPAJTFDxLQ==","assets/images/halt-creation-01-08-2020-page-11-2200x1700.png":"K0wQ6/mQiOe0RfyORTeb7w==","assets/images/halt-creation-01-08-2020-page-10-2200x1700.png":"7uH2PlnQk/4uajsUbXthVA==","assets/images/halt-creation-01-08-2020-page-12-2200x1700.png":"4Kuf0aJemECt9zwW/c4LyQ==","assets/images/screen-shot-2022-03-29-at-2.24.51-pm.png":"C/ooh+kSojDRT/0Op2R8LQ==","assets/web/assets/jquery/jquery.min.js":"3F5/GMjTasHT1HU6h8mNCg==","assets/bootstrap/css/bootstrap.min.css":"gWrw7d07SCLCdWInx+e37g==","assets/bootstrap/css/bootstrap-grid.min.css":"ZpQEaHtj4rsdGDC9wDZdfg==","assets/bootstrap/css/bootstrap-reboot.min.css":"eMZwSLVvZudwLH9xiGj50w==","assets/bootstrap/js/bootstrap.min.js":"AtIjOT4AwnPv3LGt6PT4sQ==","assets/popper/popper.min.js":"NiE4ESlZe/NNSKniYj4FyQ==","assets/tether/tether.min.css":"YhVaOUjL8Xsb9LQHyQq4Tw==","assets/tether/tether.min.js":"PlC291/0Eo8keLHUT4D9+w==","assets/theme/css/style.css":"6EUDZx+vgdwDuyFATZ5MmQ==-VITbTf54ezV7Z7I/e4lZVw==","assets/smoothscroll/smooth-scroll.js":"e15+ccLIeWb2A3ZYIotPaw==","assets/dropdown/css/style.css":"s+S8lVC62P0BWFtgHpaNFA==","assets/dropdown/js/nav-dropdown.js":"j5pq4WKLRnihd7IVVkQkJg==","assets/dropdown/js/navbar-dropdown.js":"RJXH/341Oa7csvj4pGRDfQ==","assets/touchswipe/jquery.touch-swipe.min.js":"9g/wVGnRdXmW2F9BctT/TQ==","assets/mbr-tabs/mbr-tabs.js":"CdtdEUl+8i34gHIOGPj0cQ==","assets/web/assets/mobirise-icons2/mobirise2.css":"+RO7OxVtE1FsD/N7V3/ADw==","assets/web/assets/mobirise-icons2/mobirise2.eot":"B2EjryGRojlTpzr1GHt3LQ==","assets/web/assets/mobirise-icons2/mobirise2.svg":"usCYAy7QdzckfeGReb9wWQ==","assets/web/assets/mobirise-icons2/mobirise2.ttf":"VMdAr7YYQ2ab9KiUyabAGA==","assets/web/assets/mobirise-icons2/mobirise2.woff":"xY3InaTfYGp0nlCuQBMudQ==","assets/web/assets/mobirise-icons/mobirise-icons.css":"t/IrTIzfJvbDUoCV05F+7Q==","assets/web/assets/mobirise-icons/mobirise-icons.eot":"T9iJ+Vffe7n6Gk/+pf9gEw==","assets/web/assets/mobirise-icons/mobirise-icons.svg":"Yp5pSlGdnLgPdQLUa/Yv3w==","assets/web/assets/mobirise-icons/mobirise-icons.ttf":"r0OtN8kuMaYwUc+mlGDUWA==","assets/web/assets/mobirise-icons/mobirise-icons.woff":"3aYYVAIqADvsB1jjxJZ73w==","assets/socicon/css/styles.css":"q91aZJ04O5rzI1nJO9PRHw==","assets/socicon/fonts/socicon.eot":"MvYQV8XxgngrhGqjN3oHBw==","assets/socicon/fonts/socicon.svg":"U1iRKoyNjKeR+mUJr3QbXg==","assets/socicon/fonts/socicon.ttf":"IyAo3XNB2a/Q0ml3ZraPsQ==","assets/socicon/fonts/socicon.woff":"zQDjXd6bBUQi87pRsBWVqQ==","assets/socicon/fonts/socicon.woff2":"o3w8h99EHOwP99NXAoHpOQ=="},"github://wilhelmli/":{},"file:///Users/wilhelm/Documents/GitHub/wilhelmli.github.io":{"assets/images/hashes.json":"M/7wH810xNn6ekIZ9qwv7w==","assets/images/whtffffff-172x129.png":"XgbLU/DaxYquko35r7GmYA==","assets/images/greycccccc-172x129.png":"8cLVEz2KPlZsObeFG3zBpQ==","assets/images/orange-172x129.png":"EKo2dZWz70V3Zv54ctRFqQ==","assets/images/0000ffblue-172x129.png":"jfgBfglxw2KIkX91XW6Now==","assets/images/green00ff00-172x129.png":"znj0Z8DRFpv3XIMaY0mHIg==","assets/images/yellow-172x129.png":"7brTIF2lRptklnu26BlgZw==","assets/images/li-128x128-3-128x128.png":"6DfVOezfZFomzaCEtYFtuw==","assets/images/aa-1014x1014.png":"Q6fN9N1xTFKTTcp3rPepgA==","assets/images/mbr-3-361x361.png":"KDqURiB5Exklo9oIf9ZUhw==","assets/images/mbr-4-361x361.png":"Q4TqVSNI8pNtLT7WYgK34A==","assets/images/blogcover-educhallenges-04-2020-696x392.png":"lylkT0TTAokPzwe/xJmMMw==","assets/images/07789253-267d-412f-a9f5-a446bf10e768.jpg":"WIdv6gzNrBBLURZgkTrUkw==","assets/images/img-2421.png":"k/myhI1wn4Sh6/BJGuIBEQ==","assets/images/img-9652.jpg":"7rvwboIZeMyoLbCPoIxvHg==","assets/images/img-2353.jpeg":"WiEVNuUouKcJHQZUV5pvaw==","assets/images/img-2383.jpeg":"7KuFkps7oy2vKf/GMV4ydA==","assets/images/img-5506-750x1333.jpg":"AjPmha66HYps+pSsAo50TQ==","assets/images/img-4761-750x937.jpg":"bzx2L8Pe4ul7WEMXOt/2dQ==","assets/images/img-4280-750x938.jpg":"skxwafOmVGv0j9z2IDRG5g==","assets/images/img-2960-750x500.jpg":"QFAHuMBTHcXL4qoNg6li8A==","assets/images/calcu-366x458.jpg":"7l7jAqAXih2BHuItZ+oswQ==","assets/images/halt18-20-366x459.jpg":"Zq+fEO5sBcykDDGHImOqYg==","assets/images/chessbd-366x458.jpg":"lSIkaLxm0Sfyg5hh3WTBUw==","assets/images/bauhaus-painting-366x458.jpg":"oiuQ6zAincbtRxff0ZGs9Q==","assets/images/three-tones-blkwht-366x474.jpg":"rEimpVv7PsQc6ORvLjTDnA==","assets/images/pencil-366x459.jpg":"idlgXQPw0mBza9EVkqNTVw==","assets/images/asset-9-366x457.jpg":"hMODedyBxFOsjsBgTokXNQ==","assets/images/img-9751-366x457.jpg":"3l3wuTVqMNpxTQEKqoVeUg==","assets/images/ffwht-time-2-492x377.png":"wnniaeLVECsUbbkhjOSAtw==","assets/images/owlrg-1-492x492.png":"RstS86VePUJ9zusFEOJGuQ==","assets/images/pencil-2-492x492.png":"xuKx+vC5O/gbuGGnBKZn9A==","assets/images/img-9751-366x457.jpeg":"XbS0L8tFZzOsm/ZsiByDnQ==","assets/images/owlrg-492x492.png":"AeVQuxYm0a+PAYvZSEM4lA==","assets/images/ffwht-time-492x377.png":"DgYkZjbi10yfbnyHuE4WsA==","assets/images/halt-creation-01-08-2020-page-8-1488x1150.png":"zefSjdNhj51Mp1m58quZSQ==","assets/images/sculpturewil.jpg":"ATq/Ok2ArxI6QOGbGZxIug==","assets/images/asset-78.png":"NVXIprJnKLk9aD7cryWLjQ==","assets/images/asset-32.png":"NMvCo6HHfw1OsJmti/UX2w==","assets/images/fdc4cbed-9cf4-4568-8014-bf41fb1694c0.jpg":"ZtFnw0Dv0Uy/lW5BwW9R1A==","assets/images/img-2420.png":"VI95DyMA4rrR0y6PTHOhRw==","assets/images/about-meta.jpg":"zkosLjXuTNuqsPAJNdN0cA==","assets/images/img-8271-1076x1346.jpg":"IBypIMtv3O3Pjv8LKXooAQ==","assets/images/sum-calculator-1076x1345.jpeg":"y8sM2yvEvXCefSkPRVMKOw==","assets/images/img-779-3072x4608.png":"OLRXmrHrFOf6R6OfLHYhaQ==","assets/images/img-1467.jpeg":"lqx4v8LtVJMAR4NobHGl3g==","assets/images/halt-creation-01-08-2020-page-3-1240x958.png":"wDXzZErY7FYdZjpx9A3Vfg==","assets/images/halt-creation-01-08-2020-page-3-918x709.png":"gMFKN4Fs+728WKs6Wfs1Ww==","assets/images/halt-creation-01-08-2020-page-4-1078x833.png":"FCoyEmqNtPBxKm3ohofuOQ==","assets/images/24-game-theory-halt-creation-2018.jpg":"+lDXt6VByNTf7+Wn/VfPwA==","assets/images/halt-creation-01-08-2020-page-5-1078x838.png":"Ykd4EhBt4pLXFDl0s0ZFmg==","assets/images/3-ffcc66-halt-creation-2021.png":"gZHmQPXGsECbf2GEPp+MbA==","assets/images/halt-creation-01-08-2020-page-6-1078x827.png":"zqLCFo81iXrqCdMVRz7jxA==","assets/images/img-1128-1078x1617.jpg":"jKKtBjdJx0SPP5PhnnYTaA==","assets/images/halt-creation-01-08-2020-page-7-1078x833.png":"hGcRvjnLZvQRPP4FunW41Q==","assets/images/portfolio-2020-page-17.png":"PJlieQQrIMyHzW3dgHZkfw==","assets/images/halt-creation-01-08-2020-page-9-896x692.png":"H+Hol2OQdo87lSRw8FrCcg==","assets/images/img-5734-900x1125.jpg":"1GbNGMxUPqF5lPAJTFDxLQ==","assets/images/halt-creation-01-08-2020-page-11-2200x1700.png":"K0wQ6/mQiOe0RfyORTeb7w==","assets/images/halt-creation-01-08-2020-page-10-2200x1700.png":"7uH2PlnQk/4uajsUbXthVA==","assets/images/halt-creation-01-08-2020-page-12-2200x1700.png":"4Kuf0aJemECt9zwW/c4LyQ==","assets/images/screen-shot-2022-03-29-at-2.24.51-pm.png":"C/ooh+kSojDRT/0Op2R8LQ==","assets/web/assets/jquery/jquery.min.js":"3F5/GMjTasHT1HU6h8mNCg==","assets/bootstrap/css/bootstrap.min.css":"gWrw7d07SCLCdWInx+e37g==","assets/bootstrap/css/bootstrap-grid.min.css":"ZpQEaHtj4rsdGDC9wDZdfg==","assets/bootstrap/css/bootstrap-reboot.min.css":"eMZwSLVvZudwLH9xiGj50w==","assets/bootstrap/js/bootstrap.min.js":"AtIjOT4AwnPv3LGt6PT4sQ==","assets/popper/popper.min.js":"NiE4ESlZe/NNSKniYj4FyQ==","assets/tether/tether.min.css":"YhVaOUjL8Xsb9LQHyQq4Tw==","assets/tether/tether.min.js":"PlC291/0Eo8keLHUT4D9+w==","assets/theme/css/style.css":"6EUDZx+vgdwDuyFATZ5MmQ==-VITbTf54ezV7Z7I/e4lZVw==","assets/smoothscroll/smooth-scroll.js":"e15+ccLIeWb2A3ZYIotPaw==","assets/dropdown/css/style.css":"s+S8lVC62P0BWFtgHpaNFA==","assets/dropdown/js/nav-dropdown.js":"j5pq4WKLRnihd7IVVkQkJg==","assets/dropdown/js/navbar-dropdown.js":"RJXH/341Oa7csvj4pGRDfQ==","assets/touchswipe/jquery.touch-swipe.min.js":"9g/wVGnRdXmW2F9BctT/TQ==","assets/mbr-tabs/mbr-tabs.js":"CdtdEUl+8i34gHIOGPj0cQ==","assets/web/assets/mobirise-icons2/mobirise2.css":"+RO7OxVtE1FsD/N7V3/ADw==","assets/web/assets/mobirise-icons2/mobirise2.eot":"B2EjryGRojlTpzr1GHt3LQ==","assets/web/assets/mobirise-icons2/mobirise2.svg":"usCYAy7QdzckfeGReb9wWQ==","assets/web/assets/mobirise-icons2/mobirise2.ttf":"VMdAr7YYQ2ab9KiUyabAGA==","assets/web/assets/mobirise-icons2/mobirise2.woff":"xY3InaTfYGp0nlCuQBMudQ==","assets/web/assets/mobirise-icons/mobirise-icons.css":"t/IrTIzfJvbDUoCV05F+7Q==","assets/web/assets/mobirise-icons/mobirise-icons.eot":"T9iJ+Vffe7n6Gk/+pf9gEw==","assets/web/assets/mobirise-icons/mobirise-icons.svg":"Yp5pSlGdnLgPdQLUa/Yv3w==","assets/web/assets/mobirise-icons/mobirise-icons.ttf":"r0OtN8kuMaYwUc+mlGDUWA==","assets/web/assets/mobirise-icons/mobirise-icons.woff":"3aYYVAIqADvsB1jjxJZ73w==","assets/socicon/css/styles.css":"q91aZJ04O5rzI1nJO9PRHw==","assets/socicon/fonts/socicon.eot":"MvYQV8XxgngrhGqjN3oHBw==","assets/socicon/fonts/socicon.svg":"U1iRKoyNjKeR+mUJr3QbXg==","assets/socicon/fonts/socicon.ttf":"IyAo3XNB2a/Q0ml3ZraPsQ==","assets/socicon/fonts/socicon.woff":"zQDjXd6bBUQi87pRsBWVqQ==","assets/socicon/fonts/socicon.woff2":"o3w8h99EHOwP99NXAoHpOQ==","assets/images/img-3714.jpg":"0vwjthapvm8vXHkZP/h7uQ==","assets/images/the-final-smear-by-li-haojiang-wilhelm-large.jpeg":"dPC+E7jOUke8d7FJwmCxdA==","assets/images/img-4016-large-1.jpeg":"xpWpIC37pNvuohugjn90+A==","assets/images/pkhw-blk-bg-flat.jpeg":"CDLrnj+t7mvyrw6bkY/inQ==","assets/images/08a15e3c-f64d-4908-8c4f-4fe615cdf0d3.jpg":"+bkPvRsGPsKQUtXm7cZfpQ==","assets/images/halt-fc-halt-creation-2018.png":"4dFO9QBRo0GVvo/xa8ocpQ==","assets/images/img-3694.jpg":"gc8aTBYsJ/A9xJcByJnJKQ==","assets/images/portfolio-2018-2020-brochure-3.jpeg":"QCVc+PBlVYt4wZYlo4lIJA==","assets/images/pfs-revolution.jpeg":"p3bT07xnfT2IVQIDrl9iMQ==","assets/images/orange-cirle-1-357x358.png":"2v4JUBQJRH9XTVtQBJUBZA==","assets/images/img-3716.jpg":"BV7rhsEIdh9LHg163KVOQw==","assets/images/p2022c-lihaojiang-wilhelm-0001-layer-4.png":"V9Eu/DCm2C2AK32+wuzGuw==","assets/images/p2022c-lihaojiang-wilhelm-0005-layer-8.png":"5kNXqdSCEwLULdVwbPM71w==","assets/images/pkhw-wht-bg-flat.jpg":"Gx1hhEWGhl1l2tOBIXgNCg==","assets/images/p2022c-lihaojiang-wilhelm-0004-layer-7.png":"enhAkEhFxV/yjIDiDmx5eA==","assets/images/9-ffcc66-halt-creation-2018.jpg":"Nj74iyHzrT8YARcRvuy0QQ==","assets/images/p2022c-lihaojiang-wilhelm-0003-layer-6.png":"N+wflmvvvamaACR7ZKaA+g==","assets/images/asset-5.jpg":"SXRrlklCdVl7lb9wpqXhqw==","assets/images/p2022c-lihaojiang-wilhelm-0000-layer-3.png":"X7kD5kaGVxtjEpRiwGEaxw==","assets/images/2-create-your-own-reality-halt-creation-2019.jpg":"C8TiMYavjSbJ2D00y1a3aA==","assets/images/img-8375.jpg":"5uNVouiE/2bukEoe0d4lvA==","assets/images/img-8376.jpg":"1vjmaWJ09GevhZEhQSlxkA==","assets/images/track-day-16by9-by-li-wilhelm-haojiang-at-cton-halt-creation-1.jpeg":"QVf1TOSozq/5QtxTHv4n9w==","assets/images/tesla-spring-break-watermark-free-web.jpeg":"ciMBEhQd9/wdCwadav4Xeg==","assets/images/pkhw-blk-bg-flat-1.jpeg":"CDLrnj+t7mvyrw6bkY/inQ==","assets/images/snapseed-13.jpg":"ZNMCoeAJzoQ96fnM5Bvynw==","assets/images/game-theory-energy-by-li-wilhelm-haojiang-framed-web.jpeg":"j2Z6UAF5fE/n05ohb0xbFw==","assets/images/img-3266-large.jpeg":"LDg7XlRJpqqWsWqnQJfVzQ==","assets/images/img-9525.jpg":"gKI7evMB3il4ycSRM4bsrQ==","assets/images/asset-15.png":"ID+kU5F8EamfLCAy+7Sz5A==","assets/images/track-day-16by9-by-li-wilhelm-haojiang-at-cton-halt-creation.jpg":"hAph1igGdeu5TE7V8sJkQQ==","assets/images/track-day-framed-large.jpeg":"wMVkRqiGWam2IPJ4N/dC+g==","assets/images/img-4016-large.jpeg":"4IiICCeuBn/plBUDy8qz/Q==","assets/images/floorplan.jpg":"Wnfj/cpnQEr7kKM8TVTUAA==","assets/images/19jun-ss2022-concept-1.png":"N5BGwkAFZStnMxbBL9y7IA==","assets/images/sparkstage.png":"/ACUfsNAIzdktRJ1Uo5NWQ==","assets/images/asset-11.png":"xJFS3tK9oKBzdc2nZeDhoQ==","assets/images/asset-13.png":"95K/YQcdVhe4smOUGbj+sQ==","assets/images/asset-14.png":"S0Vats0bR6jrLELcBGEnWg==","assets/images/cton-2022-meta.jpg":"hAph1igGdeu5TE7V8sJkQQ=="}}